easytqdm.py
easytqdm-1.5.dist-info/METADATA
easytqdm-1.5.dist-info/WHEEL
easytqdm-1.5.dist-info/top_level.txt
easytqdm-1.5.dist-info/RECORD
