Metadata-Version: 2.1
Name: easytqdm
Version: 1.5
Summary: easytqdm
Home-page: https://github.com/clearlyzerolxd/easytqdm
Author: LXD
Author-email: clearlyzero@stu.cqut.edu.cn
License: MIT
Platform: UNKNOWN
